__init__.py
TapisCLICICLE/__init__.py
TapisCLICICLE/__main__.py
TapisCLICICLE/serverRun.py
TapisCLICICLE/client/__init__.py
TapisCLICICLE/client/cli.py
TapisCLICICLE/client/handlers.py
TapisCLICICLE/commands/GlobusProxy.py
TapisCLICICLE/commands/__init__.py
TapisCLICICLE/commands/authenticatorClients.py
TapisCLICICLE/commands/baseCommand.py
TapisCLICICLE/commands/commandMap.py
TapisCLICICLE/commands/commandOpts.py
TapisCLICICLE/commands/dataFormatters.py
TapisCLICICLE/commands/decorators.py
TapisCLICICLE/commands/fileCommands.py
TapisCLICICLE/commands/jobCommands.py
TapisCLICICLE/commands/podCommands.py
TapisCLICICLE/commands/serverCommands.py
TapisCLICICLE/commands/snapshotCommands.py
TapisCLICICLE/commands/volumeCommands.py
TapisCLICICLE/commands/Apps/__init__.py
TapisCLICICLE/commands/Apps/appCommands.py
TapisCLICICLE/commands/Apps/appConfigGenerator.py
TapisCLICICLE/commands/Apps/appForms.py
TapisCLICICLE/commands/Systems/__init__.py
TapisCLICICLE/commands/Systems/systemCommands.py
TapisCLICICLE/commands/Systems/systemForms.py
TapisCLICICLE/commands/arguments/__init__.py
TapisCLICICLE/commands/arguments/argument.py
TapisCLICICLE/commands/arguments/argumentValidators.py
TapisCLICICLE/commands/query/__init__.py
TapisCLICICLE/commands/query/neo4j.py
TapisCLICICLE/commands/query/postgres.py
TapisCLICICLE/server/__init__.py
TapisCLICICLE/server/auth.py
TapisCLICICLE/server/server.py
TapisCLICICLE/socketopts/__init__.py
TapisCLICICLE/socketopts/schemas.py
TapisCLICICLE/socketopts/socketOpts.py
TapisCLICICLE/utilities/__init__.py
TapisCLICICLE/utilities/exceptions.py
TapisCLICICLE/utilities/killableThread.py
TapisCLICICLE/utilities/logger.py
TapisCL_ICICLE-1.0.11.dist-info/LICENSE
TapisCL_ICICLE-1.0.11.dist-info/METADATA
TapisCL_ICICLE-1.0.11.dist-info/WHEEL
TapisCL_ICICLE-1.0.11.dist-info/entry_points.txt
TapisCL_ICICLE-1.0.11.dist-info/top_level.txt
TapisCL_ICICLE-1.0.11.dist-info/RECORD
