Metadata-Version: 2.1
Name: TapisCL-ICICLE
Version: 1.0.11
Summary: Provide good performance command line user interface for Tapis services hosted on HPC clusters
Author-email: Michael Ray <m.ray37990@gmail.com>
License: GNU GENERAL PUBLIC LICENSE
Project-URL: Homepage, https://github.com/sdsc-hpc-training-org/hello_icicle_auth_clients/tree/main/icicle_rel_03_2023/CLI/TapisCL-ICICLE
Keywords: Tapis,CLI,Agave,HPC,Tapis Pods,TACC
Classifier: License :: OSI Approved :: GNU General Public License (GPL)
Classifier: Programming Language :: Python
Classifier: Programming Language :: Python :: 3
Requires-Python: >=3.6
License-File: LICENSE
Requires-Dist: pydantic ==1.10.4
Requires-Dist: pyfiglet ==0.8.post1
Requires-Dist: tapipy
Requires-Dist: blessed
Requires-Dist: pyperclip
Requires-Dist: py2neo
Requires-Dist: psycopg2-binary
Requires-Dist: prompt-toolkit
Requires-Dist: TapisFederatedAuthClientAPI
Requires-Dist: requests
Requires-Dist: questionary ==1.10.0
Provides-Extra: dev
